[
    {
        "id": "19324f111076af83",
        "type": "tab",
        "label": "Download_apis",
        "disabled": false,
        "info": "",
        "env": []
    },
    {
        "id": "d8d824f8b80f8a52",
        "type": "inject",
        "z": "19324f111076af83",
        "name": "Start",
        "props": [
            {
                "p": "payload"
            }
        ],
        "repeat": "",
        "crontab": "",
        "once": false,
        "onceDelay": "",
        "topic": "",
        "payload": "",
        "payloadType": "date",
        "x": 110,
        "y": 60,
        "wires": [
            [
                "8de49defb0fc8801",
                "b2041fb6ec26a3b6"
            ]
        ]
    },
    {
        "id": "8de49defb0fc8801",
        "type": "function",
        "z": "19324f111076af83",
        "name": "api_conso_electrique_agregats_30min_points_soutirage_all",
        "func": "// Initialisation\n\nconst NomFile = node.name + '.json';\nconst filePath = \"/data/\" + NomFile;   // <-- IMPORTANT\nflow.set('allResults', []);\nflow.set('pageCount', 0);\nflow.set('NomFile', NomFile );\n\nconst firstUrl = 'https://opendata.enedis.fr/data-fair/api/v1/datasets/conso-sup36-region/lines?page=1&format=json&size=5000';\nflow.set('nextUrl', firstUrl);\n\nmsg.payload = filePath ;\nmsg.url = firstUrl;\nnode.warn('Fichier à supprimer: ' + filePath);\nnode.warn('Démarrage - URL: ' + firstUrl);\nreturn msg;",
        "outputs": 1,
        "timeout": "",
        "noerr": 0,
        "initialize": "",
        "finalize": "",
        "libs": [],
        "x": 460,
        "y": 40,
        "wires": [
            [
                "aa6699c7ec5a753a"
            ]
        ]
    },
    {
        "id": "e55a44baff75abb8",
        "type": "http request",
        "z": "19324f111076af83",
        "name": "Fetch Page",
        "method": "GET",
        "ret": "obj",
        "paytoqs": "ignore",
        "url": "",
        "tls": "",
        "persist": false,
        "proxy": "",
        "insecureHTTPParser": false,
        "authType": "",
        "senderr": false,
        "headers": [],
        "x": 370,
        "y": 160,
        "wires": [
            [
                "37779faa15868db2"
            ]
        ]
    },
    {
        "id": "37779faa15868db2",
        "type": "function",
        "z": "19324f111076af83",
        "name": "Process & Check Next",
        "func": "const data = msg.payload;\nconst max = 2;\n\n// Vérification erreur HTTP\nif (msg.statusCode !== 200) {\n    node.error('Erreur HTTP: ' + msg.statusCode);\n    return null;\n}\n\nconst newResults = data.results;\n\nconst valuLigne =  data.length + flow.get('valuLigne') || 0 \nflow.set('valuLigne', valuLigne);\n\n\n// Compteur de pages\nconst pageCount = (flow.get('pageCount') || 0) + 1;\nflow.set('pageCount', pageCount);\n\nnode.warn(`Page récupérée : ${pageCount} pour ${valuLigne} lignes au total`);\n\n// Déterminer si premier passage\nconst isFirst = pageCount === 1;\n\n// Déterminer si dernier passage\nconst isLast = !data.next ;//|| pageCount >= max;\n\n// Construction du chunk JSON\nlet chunk = \"\";\n\n// ➜ début du tableau\nif (isFirst) {\n    chunk += \"[\";\n}\n\n// ➜ contenu (sans [] autour)\nchunk += newResults.map(obj => JSON.stringify(obj)).join(\",\\n\");\n\n// ➜ fin du tableau\nif (isLast) {\n    chunk += \"]\";\n} else {\n    chunk += \",\\n\";\n}\n\n// Conversion en buffer\nconst fileName = flow.get('NomFile');\nmsg.payload = Buffer.from(chunk);\nmsg.filename = '/data/' + fileName;\n\nnode.warn(`Page ${pageCount} - ${newResults.length} résultats`);\n\n// Pagination\nif (!isLast) {\n    msg.url = data.next;\n    return [msg, null];\n} else {\n    node.warn('Pagination terminée');\n    return [null, msg];\n}",
        "outputs": 2,
        "timeout": "",
        "noerr": 0,
        "initialize": "",
        "finalize": "",
        "libs": [],
        "x": 600,
        "y": 160,
        "wires": [
            [
                "b80858c0d477f2e2"
            ],
            [
                "906665dfadfea120"
            ]
        ]
    },
    {
        "id": "906665dfadfea120",
        "type": "file",
        "z": "19324f111076af83",
        "name": "Save File",
        "filename": "filename",
        "filenameType": "msg",
        "appendNewline": true,
        "createDir": true,
        "overwriteFile": "false",
        "encoding": "none",
        "x": 840,
        "y": 180,
        "wires": [
            [
                "38da367522bb4eb7"
            ]
        ]
    },
    {
        "id": "7dfefa7eb3938d4a",
        "type": "exec",
        "z": "19324f111076af83",
        "command": "",
        "addpay": "payload",
        "append": "",
        "useSpawn": "false",
        "timer": "",
        "winHide": false,
        "oldrc": false,
        "name": "Upload to MinIO",
        "x": 1100,
        "y": 140,
        "wires": [
            [
                "debug_success"
            ],
            [
                "debug_error"
            ],
            []
        ]
    },
    {
        "id": "38da367522bb4eb7",
        "type": "function",
        "z": "19324f111076af83",
        "name": "Build MinIO Command",
        "func": "const filePath = msg.filename;\n// filePath = '/data/nom_fichier.json'\n\nconst fileName = filePath.split('/').pop();\n// fileName = 'nom_fichier.json'\n\nconst minioDest = 'local/datalake/' + fileName;\n\nmsg.payload = `mc alias set local http://minio:9000 admin password && mc cp ${filePath} ${minioDest}`;\n\nnode.warn('Commande MinIO: ' + msg.payload);\nreturn msg;",
        "outputs": 1,
        "timeout": "",
        "noerr": 0,
        "initialize": "",
        "finalize": "",
        "libs": [],
        "x": 1000,
        "y": 40,
        "wires": [
            [
                "7dfefa7eb3938d4a"
            ]
        ]
    },
    {
        "id": "b2041fb6ec26a3b6",
        "type": "function",
        "z": "19324f111076af83",
        "name": "Init Download Parquet",
        "func": "const fileName = 'calendrier_vacances_scolaires_france.parquet';\nconst url = 'https://object.files.data.gouv.fr/hydra-parquet/hydra-parquet/c3781037-dffb-4789-9af9-15a955336771.parquet';\n\nflow.set('fileName', fileName);\nflow.set('filePath', '/data/' + fileName);\n\nmsg.url = url;\nnode.warn('Démarrage téléchargement: ' + url);\nreturn msg;",
        "outputs": 1,
        "timeout": "",
        "noerr": 0,
        "initialize": "",
        "finalize": "",
        "libs": [],
        "x": 160,
        "y": 300,
        "wires": [
            [
                "c3f5a1d2e4b67890"
            ]
        ]
    },
    {
        "id": "c3f5a1d2e4b67890",
        "type": "http request",
        "z": "19324f111076af83",
        "name": "Download Parquet",
        "method": "GET",
        "ret": "bin",
        "paytoqs": "ignore",
        "url": "",
        "tls": "",
        "persist": false,
        "proxy": "",
        "insecureHTTPParser": false,
        "authType": "",
        "senderr": false,
        "headers": [],
        "x": 130,
        "y": 440,
        "wires": [
            [
                "d4e6b2c1f5a78901"
            ]
        ]
    },
    {
        "id": "d4e6b2c1f5a78901",
        "type": "function",
        "z": "19324f111076af83",
        "name": "Check HTTP Response",
        "func": "if (msg.statusCode !== 200) {\n    node.error('Erreur HTTP: ' + msg.statusCode, msg);\n    return null;\n}\n\nconst filePath = flow.get('filePath');\nconst fileName = flow.get('fileName');\n\nnode.warn('Téléchargement OK - Taille: ' + msg.payload.length + ' bytes');\n\nmsg.filename = filePath;\nmsg.fileName = fileName;\nreturn msg;",
        "outputs": 1,
        "timeout": "",
        "noerr": 0,
        "initialize": "",
        "finalize": "",
        "libs": [],
        "x": 390,
        "y": 440,
        "wires": [
            [
                "e5f7c3d2a6b89012"
            ]
        ]
    },
    {
        "id": "e5f7c3d2a6b89012",
        "type": "file",
        "z": "19324f111076af83",
        "name": "Save Parquet",
        "filename": "filename",
        "filenameType": "msg",
        "appendNewline": false,
        "createDir": true,
        "overwriteFile": "true",
        "encoding": "none",
        "x": 640,
        "y": 440,
        "wires": [
            [
                "f6a8d4e3b7c90123"
            ]
        ]
    },
    {
        "id": "f6a8d4e3b7c90123",
        "type": "function",
        "z": "19324f111076af83",
        "name": "Build MinIO Command",
        "func": "const filePath = msg.filename;\n// filePath = '/data/nom_fichier.parquet'\n\nconst fileName = filePath.split('/').pop();\n// fileName = 'nom_fichier.parquet'\n\nconst minioDest = 'local/datalake/' + fileName;\n\nmsg.payload = `mc alias set local http://minio:9000 admin password && mc cp ${filePath} ${minioDest}`;\n\nnode.warn('Commande MinIO: ' + msg.payload);\nreturn msg;",
        "outputs": 1,
        "timeout": "",
        "noerr": 0,
        "initialize": "",
        "finalize": "",
        "libs": [],
        "x": 160,
        "y": 560,
        "wires": [
            [
                "a1b2c3d4e5f60123"
            ]
        ]
    },
    {
        "id": "debug_success",
        "type": "debug",
        "z": "19324f111076af83",
        "name": "Upload OK",
        "active": true,
        "tosidebar": true,
        "console": false,
        "tostatus": false,
        "complete": "payload",
        "x": 1190,
        "y": 240,
        "wires": []
    },
    {
        "id": "debug_error",
        "type": "debug",
        "z": "19324f111076af83",
        "name": "Upload ERROR",
        "active": true,
        "tosidebar": true,
        "console": false,
        "tostatus": false,
        "complete": "payload",
        "x": 1200,
        "y": 300,
        "wires": []
    },
    {
        "id": "debug_timeout",
        "type": "debug",
        "z": "19324f111076af83",
        "name": "Upload TIMEOUT",
        "active": true,
        "tosidebar": true,
        "console": false,
        "tostatus": false,
        "complete": "payload",
        "x": 1190,
        "y": 400,
        "wires": []
    },
    {
        "id": "a1b2c3d4e5f60123",
        "type": "exec",
        "z": "19324f111076af83",
        "command": "",
        "addpay": "payload",
        "append": "",
        "useSpawn": "false",
        "timer": "60",
        "winHide": false,
        "oldrc": false,
        "name": "Upload to MinIO",
        "x": 620,
        "y": 560,
        "wires": [
            [
                "debug_success"
            ],
            [
                "debug_error"
            ],
            [
                "debug_timeout"
            ]
        ]
    },
    {
        "id": "b80858c0d477f2e2",
        "type": "file",
        "z": "19324f111076af83",
        "name": "Save File",
        "filename": "filename",
        "filenameType": "msg",
        "appendNewline": true,
        "createDir": true,
        "overwriteFile": "false",
        "encoding": "none",
        "x": 440,
        "y": 300,
        "wires": [
            [
                "e55a44baff75abb8"
            ]
        ]
    },
    {
        "id": "aa6699c7ec5a753a",
        "type": "exec",
        "z": "19324f111076af83",
        "command": "rm -f ",
        "addpay": "payload",
        "append": "",
        "useSpawn": "false",
        "timer": "",
        "winHide": false,
        "oldrc": false,
        "name": "",
        "x": 750,
        "y": 40,
        "wires": [
            [
                "e55a44baff75abb8"
            ],
            [],
            []
        ]
    }
]